LICENSE
README.md
setup.cfg
setup.py
smscx_client/__init__.py
smscx_client/api_client.py
smscx_client/configuration.py
smscx_client/exceptions.py
smscx_client/model_utils.py
smscx_client/rest.py
smscx_client.egg-info/PKG-INFO
smscx_client.egg-info/SOURCES.txt
smscx_client.egg-info/dependency_links.txt
smscx_client.egg-info/requires.txt
smscx_client.egg-info/top_level.txt
smscx_client/api/__init__.py
smscx_client/api/account_api.py
smscx_client/api/applications_api.py
smscx_client/api/attachments_api.py
smscx_client/api/conversations_api.py
smscx_client/api/groups_api.py
smscx_client/api/multichannel_api.py
smscx_client/api/numbers_api.py
smscx_client/api/oauth_api.py
smscx_client/api/optouts_api.py
smscx_client/api/originators_api.py
smscx_client/api/otp_api.py
smscx_client/api/reports_api.py
smscx_client/api/shortlinks_api.py
smscx_client/api/sms_api.py
smscx_client/api/templates_api.py
smscx_client/api/viber_api.py
smscx_client/api/whatsapp_api.py
smscx_client/apis/__init__.py
smscx_client/model/__init__.py
smscx_client/model/accepted.py
smscx_client/model/account_balance.py
smscx_client/model/add_contacts_to_group400_response.py
smscx_client/model/add_contacts_to_group_request.py
smscx_client/model/add_contacts_to_group_response.py
smscx_client/model/add_contacts_to_group_with_fields_request.py
smscx_client/model/alerts.py
smscx_client/model/application_settings_response.py
smscx_client/model/applications_list_response.py
smscx_client/model/attachment_delete_response.py
smscx_client/model/attachment_details_response.py
smscx_client/model/attachment_list_response.py
smscx_client/model/attachments.py
smscx_client/model/bulk_lookup_campaigns_response.py
smscx_client/model/call_back_request_attachment_hit.py
smscx_client/model/call_back_request_dlr_update.py
smscx_client/model/call_back_request_new_optout.py
smscx_client/model/call_back_request_number_lookup.py
smscx_client/model/call_back_request_otp_update.py
smscx_client/model/call_back_request_receive_sms.py
smscx_client/model/call_back_request_shortlink_hit.py
smscx_client/model/callback_event_types.py
smscx_client/model/campaigns.py
smscx_client/model/cancel_otp_response.py
